{
	"info": {
		"_postman_id": "b1ccb7f0-0a5a-4e0d-aff4-df7bfe089630",
		"name": "学生管理系统",
		"schema": "https://schema.getpostman.com/json/collection/v2.1.0/collection.json"
	},
	"item": [
		{
			"name": "登录",
			"item": [
				{
					"name": "用户名正确——密码错误",
					"request": {
						"method": "POST",
						"header": [
							{
								"key": "Content-Type",
								"name": "Content-Type",
								"value": "application/json",
								"type": "text"
							}
						],
						"body": {
							"mode": "raw",
							"raw": "{\"sname\":\"tom\",\"pwd\":\"1111\"}",
							"options": {
								"raw": {
									"language": "json"
								}
							}
						},
						"url": {
							"raw": "http://localhost:8888/sms/login.action",
							"protocol": "http",
							"host": [
								"localhost"
							],
							"port": "8888",
							"path": [
								"sms",
								"login.action"
							]
						}
					},
					"response": []
				},
				{
					"name": "用户名错误——密码正确",
					"request": {
						"method": "POST",
						"header": [
							{
								"key": "Content-Type",
								"name": "Content-Type",
								"value": "application/json",
								"type": "text"
							}
						],
						"body": {
							"mode": "raw",
							"raw": "{\"sname\":\"tom\",\"pwd\":\"1111\"}",
							"options": {
								"raw": {
									"language": "json"
								}
							}
						},
						"url": {
							"raw": "http://localhost:8888/sms/login.action",
							"protocol": "http",
							"host": [
								"localhost"
							],
							"port": "8888",
							"path": [
								"sms",
								"login.action"
							]
						}
					},
					"response": []
				},
				{
					"name": "用户名错—— 密码错误",
					"request": {
						"method": "POST",
						"header": [
							{
								"key": "Content-Type",
								"name": "Content-Type",
								"value": "application/json",
								"type": "text"
							}
						],
						"body": {
							"mode": "raw",
							"raw": "{\"sname\":\"tom\",\"pwd\":\"1111\"}",
							"options": {
								"raw": {
									"language": "json"
								}
							}
						},
						"url": {
							"raw": "http://localhost:8888/sms/login.action",
							"protocol": "http",
							"host": [
								"localhost"
							],
							"port": "8888",
							"path": [
								"sms",
								"login.action"
							]
						}
					},
					"response": []
				},
				{
					"name": "用户名为空",
					"event": [
						{
							"listen": "prerequest",
							"script": {
								"id": "2325e431-da18-462d-8f4f-aa90ac372820",
								"exec": [
									""
								],
								"type": "text/javascript"
							}
						}
					],
					"request": {
						"method": "POST",
						"header": [
							{
								"key": "Content-Type",
								"name": "Content-Type",
								"value": "application/json",
								"type": "text"
							}
						],
						"body": {
							"mode": "raw",
							"raw": "{\"sname\":\"\",\"pwd\":\"111\"}",
							"options": {
								"raw": {
									"language": "json"
								}
							}
						},
						"url": {
							"raw": "http://localhost:8888/sms/login.action",
							"protocol": "http",
							"host": [
								"localhost"
							],
							"port": "8888",
							"path": [
								"sms",
								"login.action"
							]
						}
					},
					"response": []
				},
				{
					"name": "用户名——密码正确",
					"request": {
						"method": "POST",
						"header": [
							{
								"key": "Content-Type",
								"name": "Content-Type",
								"value": "application/json",
								"type": "text"
							}
						],
						"body": {
							"mode": "raw",
							"raw": "{\"sname\":\"tom\",\"pwd\":\"111\"}",
							"options": {
								"raw": {
									"language": "json"
								}
							}
						},
						"url": {
							"raw": "http://localhost:8888/sms/login.action",
							"protocol": "http",
							"host": [
								"localhost"
							],
							"port": "8888",
							"path": [
								"sms",
								"login.action"
							]
						}
					},
					"response": []
				}
			],
			"protocolProfileBehavior": {}
		},
		{
			"name": "注册",
			"item": [
				{
					"name": "用户名——密码不为空",
					"request": {
						"method": "POST",
						"header": [
							{
								"key": "Content-Type",
								"name": "Content-Type",
								"value": "application/json",
								"type": "text"
							}
						],
						"body": {
							"mode": "raw",
							"raw": "{\"sname\":\"make\",\"pwd\":\"444\",\"sage\":11,\"address\":\"上海\"}",
							"options": {
								"raw": {
									"language": "json"
								}
							}
						},
						"url": {
							"raw": "http://localhost:8888/sms/regist.action",
							"protocol": "http",
							"host": [
								"localhost"
							],
							"port": "8888",
							"path": [
								"sms",
								"regist.action"
							]
						}
					},
					"response": []
				},
				{
					"name": "用户名为空",
					"request": {
						"method": "POST",
						"header": [
							{
								"key": "Content-Type",
								"name": "Content-Type",
								"value": "application/json",
								"type": "text"
							}
						],
						"body": {
							"mode": "raw",
							"raw": "{\"sname\":\"\",\"pwd\":\"444\"}",
							"options": {
								"raw": {
									"language": "json"
								}
							}
						},
						"url": {
							"raw": "http://localhost:8888/sms/regist.action",
							"protocol": "http",
							"host": [
								"localhost"
							],
							"port": "8888",
							"path": [
								"sms",
								"regist.action"
							]
						}
					},
					"response": []
				},
				{
					"name": "密码为空",
					"request": {
						"method": "POST",
						"header": [
							{
								"key": "Content-Type",
								"name": "Content-Type",
								"value": "application/json",
								"type": "text"
							}
						],
						"body": {
							"mode": "raw",
							"raw": "{\"sname\":\"ABC\",\"pwd\":\"\"}",
							"options": {
								"raw": {
									"language": "json"
								}
							}
						},
						"url": {
							"raw": "http://localhost:8888/sms/regist.action",
							"protocol": "http",
							"host": [
								"localhost"
							],
							"port": "8888",
							"path": [
								"sms",
								"regist.action"
							]
						}
					},
					"response": []
				},
				{
					"name": "用户名、密码为空",
					"request": {
						"method": "POST",
						"header": [
							{
								"key": "Content-Type",
								"name": "Content-Type",
								"value": "application/json",
								"type": "text"
							}
						],
						"body": {
							"mode": "raw",
							"raw": "{\"sname\":\"\",\"pwd\":\"\"}",
							"options": {
								"raw": {
									"language": "json"
								}
							}
						},
						"url": {
							"raw": "http://localhost:8888/sms/regist.action",
							"protocol": "http",
							"host": [
								"localhost"
							],
							"port": "8888",
							"path": [
								"sms",
								"regist.action"
							]
						}
					},
					"response": []
				},
				{
					"name": "用户名有特殊字符",
					"request": {
						"method": "POST",
						"header": [
							{
								"key": "Content-Type",
								"name": "Content-Type",
								"value": "application/json",
								"type": "text"
							}
						],
						"body": {
							"mode": "raw",
							"raw": "{\"sname\":\"ABC_*\",\"pwd\":\"555\"}",
							"options": {
								"raw": {
									"language": "json"
								}
							}
						},
						"url": {
							"raw": "http://localhost:8888/sms/regist.action",
							"protocol": "http",
							"host": [
								"localhost"
							],
							"port": "8888",
							"path": [
								"sms",
								"regist.action"
							]
						}
					},
					"response": []
				}
			],
			"protocolProfileBehavior": {}
		},
		{
			"name": "删除学生",
			"item": [
				{
					"name": "获取ID删除",
					"request": {
						"method": "GET",
						"header": [],
						"url": {
							"raw": "http://localhost:8888/sms/deleteBySid.action?sid=7",
							"protocol": "http",
							"host": [
								"localhost"
							],
							"port": "8888",
							"path": [
								"sms",
								"deleteBySid.action"
							],
							"query": [
								{
									"key": "sid",
									"value": "7"
								}
							]
						}
					},
					"response": []
				}
			],
			"protocolProfileBehavior": {}
		},
		{
			"name": "查询所有学生信息",
			"item": [
				{
					"name": "所有学生的接口",
					"request": {
						"method": "GET",
						"header": [],
						"url": {
							"raw": "http://localhost:8888/sms/findAll.action",
							"protocol": "http",
							"host": [
								"localhost"
							],
							"port": "8888",
							"path": [
								"sms",
								"findAll.action"
							]
						}
					},
					"response": []
				}
			],
			"protocolProfileBehavior": {}
		}
	],
	"protocolProfileBehavior": {}
}